{"version":"1.0.0","name":"skincollection","dependencies":{"@react-native-async-storage/async-storage":{"version":"1.17.11"},"@react-native-community/masked-view":{"version":"0.1.11"},"@react-navigation/bottom-tabs":{"version":"6.5.7"},"@react-navigation/drawer":{"version":"6.6.2"},"@react-navigation/native":{"version":"6.1.6"},"@react-navigation/stack":{"version":"6.3.16"},"expo-font":{"version":"11.1.1"},"expo-linear-gradient":{"version":"12.1.2"},"expo-secure-store":{"version":"12.1.1"},"expo-status-bar":{"version":"1.4.4"},"expo":{"version":"48.0.19"},"json-query":{"version":"2.2.2"},"react-native-circular-progress":{"version":"1.3.9"},"react-native-drop-shadow":{"version":"0.0.7"},"react-native-gesture-handler":{"version":"2.9.0"},"react-native-global-props":{"version":"1.1.5"},"react-native-linear-gradient":{"version":"2.7.3"},"react-native-paper":{"version":"5.8.0"},"react-native-push-notification-popup":{"version":"1.6.1"},"react-native-reanimated":{"version":"2.14.4"},"react-native-safe-area-context":{"version":"4.5.0"},"react-native-screens":{"version":"3.20.0"},"react-native-splash-screen":{"version":"3.3.0"},"react-native-svg":{"version":"13.4.0"},"react-native-vector-icons":{"version":"9.2.0"},"react-native":{"version":"0.71.8"},"react-redux":{"version":"8.1.1"},"react":{"version":"18.2.0"}}}